{
	"id": "witch_chatter_friendship5_1",
	"title": "[1] witch chatter at friendship level: friendship5",
	"description": "dialog.npc.witch.chatter.description",
	"allowClose": true,
	"entries": [
		{
			"id": "start",
			"speaker": {
				"translate": "dialog.npc.witch.name",
				"color": "white"
			},
			"text": [
				{
					"translate": "dialog.npc.witch.chatter_friendship5.1.line_0"
				}
			],
			"portraits": [
				{
					"path": "witch.png",
					"position": "INLINE",
					"brightness": 1
				}
			],
			"command": [
				"openshop @p witch"
			]
		}
	]
}